sleeper_wrapper/__init__.py
sleeper_wrapper/base_api.py
sleeper_wrapper/drafts.py
sleeper_wrapper/league.py
sleeper_wrapper/players.py
sleeper_wrapper/stats.py
sleeper_wrapper/user.py
sleeper_wrapper-1.1.0.dist-info/LICENSE.md
sleeper_wrapper-1.1.0.dist-info/METADATA
sleeper_wrapper-1.1.0.dist-info/WHEEL
sleeper_wrapper-1.1.0.dist-info/RECORD
