Metadata-Version: 2.1
Name: sleeper-wrapper
Version: 1.1.0
Summary: A Python API wrapper for Sleeper Fantasy sports, as well as tools to simplify received data.
Home-page: https://github.com/dtsong/sleeper-api-wrapper
License: MIT
Keywords: fantasy football,fantasy sports,sports,sleeper fantasy,sleeper
Author: Dan Song, Ford Higgins
Author-email: py-sleeper-api-wrapper-maintainers@googlegroups.com
Requires-Python: >=3.9,<4.0
Classifier: License :: OSI Approved :: MIT License
Classifier: Programming Language :: Python
Classifier: Programming Language :: Python :: 3
Classifier: Programming Language :: Python :: 3.9
Classifier: Programming Language :: Python :: 3.10
Classifier: Programming Language :: Python :: 3.11
Classifier: Programming Language :: Python :: 3.12
Classifier: Programming Language :: Python ::  3
Requires-Dist: requests (>=2.22.0,<3.0.0)
Project-URL: Documentation, https://github.com/dtsong/sleeper-api-wrapper/tree/master/docs
Project-URL: Repository, https://github.com/dtsong/sleeper-api-wrapper
